arrowshelf-2.3.1.data/scripts/arrowshelfd.exe
arrowshelf-2.3.1.dist-info/METADATA
arrowshelf-2.3.1.dist-info/WHEEL
arrowshelf-2.3.1.dist-info/licenses/LICENSE
arrowshelf/__init__.py
arrowshelf/client.py
arrowshelf/exceptions.py
arrowshelf/server.py
arrowshelf-2.3.1.dist-info/RECORD
