Metadata-Version: 2.4
Name: arrowshelf
Version: 2.3.1
Classifier: License :: OSI Approved :: MIT License
Classifier: Programming Language :: Python
Classifier: Programming Language :: Python :: 3
Classifier: Programming Language :: Rust
Classifier: Topic :: Software Development :: Libraries :: Python Modules
Classifier: Intended Audience :: Developers
Classifier: Intended Audience :: Science/Research
Classifier: Operating System :: OS Independent
Requires-Dist: pandas>=1.0
Requires-Dist: pyarrow>=10.0
Requires-Dist: numba ; extra == 'numba'
Provides-Extra: numba
License-File: LICENSE
Summary: A lightning-fast, zero-copy, cross-process data store for Python using Apache Arrow and shared memory.
Author-email: Your Name <your@email.com>
Requires-Python: >=3.8
Project-URL: Homepage, https://github.com/your-username/arrowshelf
Project-URL: Repository, https://github.com/your-username/arrowshelf
